{
  "users": [
    {
      "id": "1",
      "name": "xavi",
      "email": "a@gmail.com",
      "password": "123456"
    },
    {
      "id": "dafc0649-def0-4cf8-8ad3-741f06b86818",
      "email": "b@gmail.com",
      "password": "$2a$08$3vYWAnCos5s1GUakSV6e1.B6q.7uCSWQ2KYjIqNagtuzy8tZ5g.Wa"
    },
    {
      "id": "c947b609-eeda-4e55-8782-8ccbf08f6468",
      "email": "c@gmail.com",
      "password": "$2a$08$ph1lG6DetHzBZMLC8MybguoZhQ0fmkh5gVqaxJbbf3AuEUw2hA5dG"
    }
  ],
  "boards": [
    {
      "id": "1",
      "title": "Proyecto 1",
      "user_id": "dafc0649-def0-4cf8-8ad3-741f06b86818"
    },
    {
      "id": "fb6650e3-50a8-4272-825e-79b85afa7436",
      "title": "a",
      "user_id": "dafc0649-def0-4cf8-8ad3-741f06b86818"
    }
  ],
  "lists": [
    {
      "id": "1",
      "title": "Por Hacer",
      "createdDate": "2024-02-10T12:00:00Z",
      "color": "#ff5733",
      "isArchived": false,
      "boardId": "fb6650e3-50a8-4272-825e-79b85afa7436"
    },
    {
      "id": "baabe817-4765-4263-a5fd-36edf4a339e1",
      "title": "aaa",
      "createdDate": "2025-02-13T18:25:45.161Z",
      "color": "gray",
      "isArchived": false,
      "boardId": "1",
      "tasks": []
    },
    {
      "id": "9d892e24-277c-4210-a020-48ece77f4f15",
      "title": "adsas",
      "createdDate": "2025-02-13T18:28:51.899Z",
      "color": "gray",
      "isArchived": false,
      "boardId": "1",
      "tasks": []
    },
    {
      "id": "166d33ca-dd56-4d1e-a53f-a7303d49bfb7",
      "title": "sadasds",
      "createdDate": "2025-02-13T18:28:53.208Z",
      "color": "gray",
      "isArchived": false,
      "boardId": "1",
      "tasks": []
    }
  ],
  "tasks": []
}